django_qingstor_storage/__init__.py
django_qingstor_storage/backends.py
django_qingstor_storage-0.1.2.dist-info/METADATA
django_qingstor_storage-0.1.2.dist-info/RECORD
django_qingstor_storage-0.1.2.dist-info/WHEEL
django_qingstor_storage-0.1.2.dist-info/top_level.txt
