Metadata-Version: 2.1
Name: django-qingstor-storage
Version: 0.1.2
Summary: Django storage with Qingstor
Home-page: https://github.com/knktc/django-qingstor-storage
Author: knktc
Author-email: me@knktc.com
License: UNKNOWN
Platform: UNKNOWN
Classifier: Programming Language :: Python :: 3
Classifier: License :: OSI Approved :: MIT License
Classifier: Operating System :: OS Independent
Classifier: Framework :: Django
Classifier: Intended Audience :: Developers
Requires-Dist: django (>=2.0)
Requires-Dist: qingstor-sdk (>=2.2.6)
